paperpy/__init__.py
paperpy/exceptions.py
paperpy/interfaces.py
paperpy/paperpy.py
paperpy/data/de/attentionwords.txt
paperpy/data/de/ngramlist.txt
paperpy-0.0.1b2.dist-info/LICENSE
paperpy-0.0.1b2.dist-info/METADATA
paperpy-0.0.1b2.dist-info/WHEEL
paperpy-0.0.1b2.dist-info/entry_points.txt
paperpy-0.0.1b2.dist-info/top_level.txt
paperpy-0.0.1b2.dist-info/RECORD
