Metadata-Version: 2.1
Name: paperpy
Version: 0.0.1b2
Summary: Tools for simplifying the preparation of version-controlled and well-written academic papers.
Home-page: https://github.com/paperpy/paperpy
Author: Robin De Schepper
Author-email: robingilbert.deschepper@unipv.it
License: MIT
Keywords: paper academia academic writing write
Platform: UNKNOWN
Classifier: Intended Audience :: Science/Research
Classifier: License :: OSI Approved :: MIT License
Classifier: Operating System :: OS Independent
Classifier: Programming Language :: Python
Requires-Dist: setuptools
Requires-Dist: pypandoc
Requires-Dist: tabulate
Requires-Dist: textblob
Provides-Extra: dev
Requires-Dist: sphinx ; extra == 'dev'
Requires-Dist: sphinx-rtd-theme (>=0.4.3) ; extra == 'dev'
Requires-Dist: pre-commit ; extra == 'dev'
Requires-Dist: black ; extra == 'dev'
